titan_plugin_git/__init__.py
titan_plugin_git/clients/__init__.py
titan_plugin_git/clients/git_client.py
titan_plugin_git/exceptions.py
titan_plugin_git/messages.py
titan_plugin_git/models.py
titan_plugin_git/plugin.py
titan_plugin_git/steps/__init__.py
titan_plugin_git/steps/ai_commit_message_step.py
titan_plugin_git/steps/branch_steps.py
titan_plugin_git/steps/commit_step.py
titan_plugin_git/steps/diff_summary_step.py
titan_plugin_git/steps/push_step.py
titan_plugin_git/steps/status_step.py
titan_plugin_git/workflows/__previews__/__init__.py
titan_plugin_git/workflows/__previews__/commit_ai_preview.py
titan_plugin_git/workflows/commit-ai.yaml
titan_plugin_github/__init__.py
titan_plugin_github/agents/__init__.py
titan_plugin_github/agents/config_loader.py
titan_plugin_github/agents/issue_generator.py
titan_plugin_github/agents/pr_agent.py
titan_plugin_github/clients/__init__.py
titan_plugin_github/clients/github_client.py
titan_plugin_github/config/__init__.py
titan_plugin_github/config/pr_agent.toml
titan_plugin_github/exceptions.py
titan_plugin_github/messages.py
titan_plugin_github/models.py
titan_plugin_github/plugin.py
titan_plugin_github/steps/__init__.py
titan_plugin_github/steps/ai_pr_step.py
titan_plugin_github/steps/create_pr_step.py
titan_plugin_github/steps/github_prompt_steps.py
titan_plugin_github/steps/issue_steps.py
titan_plugin_github/steps/preview_step.py
titan_plugin_github/utils.py
titan_plugin_github/workflows/__previews__/__init__.py
titan_plugin_github/workflows/__previews__/create_pr_ai_preview.py
titan_plugin_github/workflows/create-issue-ai.yaml
titan_plugin_github/workflows/create-pr-ai.yaml
titan_plugin_jira/__init__.py
titan_plugin_jira/agents/__init__.py
titan_plugin_jira/agents/config_loader.py
titan_plugin_jira/agents/jira_agent.py
titan_plugin_jira/agents/prompts.py
titan_plugin_jira/agents/response_parser.py
titan_plugin_jira/agents/token_tracker.py
titan_plugin_jira/agents/validators.py
titan_plugin_jira/clients/jira_client.py
titan_cli-0.1.5.dist-info/METADATA
titan_cli-0.1.5.dist-info/WHEEL
titan_cli-0.1.5.dist-info/entry_points.txt
titan_cli-0.1.5.dist-info/licenses/LICENSE
titan_cli-0.1.5.dist-info/RECORD
