Metadata-Version: 2.4
Name: titan-cli
Version: 0.1.5
Summary: Modular development tools orchestrator - Streamline your workflows with AI integration and intuitive terminal UI
License: MIT
License-File: LICENSE
Keywords: cli,workflow,orchestrator,automation,devtools,ai
Author: finxo
Author-email: finxeto@gmail.com
Maintainer: r-pedraza
Maintainer-email: raulpedrazaleon@gmail.com
Requires-Python: >=3.10,<4.0.0
Classifier: Development Status :: 5 - Production/Stable
Classifier: Environment :: Console
Classifier: Intended Audience :: Developers
Classifier: License :: OSI Approved :: MIT License
Classifier: Operating System :: OS Independent
Classifier: Programming Language :: Python :: 3
Classifier: Programming Language :: Python :: 3.10
Classifier: Programming Language :: Python :: 3.11
Classifier: Programming Language :: Python :: 3.12
Classifier: Programming Language :: Python :: 3.13
Classifier: Programming Language :: Python :: 3.14
Requires-Dist: anthropic (>=0.75.0,<0.76.0)
Requires-Dist: google-auth (>=2.43.0,<3.0.0)
Requires-Dist: google-genai (>=1.58.0,<2.0.0)
Requires-Dist: jinja2 (>=3.1.4,<4.0.0)
Requires-Dist: keyring (>=25.7.0,<26.0.0)
Requires-Dist: packaging (>=23.0,<25.0)
Requires-Dist: pydantic (>=2.0.0,<3.0.0)
Requires-Dist: python-dotenv (>=1.2.1,<2.0.0)
Requires-Dist: pyyaml (>=6.0.3,<7.0.0)
Requires-Dist: requests (>=2.31.0,<3.0.0)
Requires-Dist: textual (>=1.0.0,<2.0.0)
Requires-Dist: tomli (>=2.0.0,<3.0.0)
Requires-Dist: tomli-w (>=1.0.0,<2.0.0)
Requires-Dist: typer (>=0.20.0,<1.0.0)
Project-URL: Documentation, https://github.com/masmovil/titan-cli
Project-URL: Homepage, https://github.com/masmovil/titan-cli
Project-URL: Repository, https://github.com/masmovil/titan-cli
